{
  "run_id": "20260329-6f22c0fc",
  "agent": "data_collector",
  "schema_version": 2,
  "ticker": "NVDA",
  "company_name": "NVIDIA Corporation",
  "report_date": "2026-03-29",
  "payload": {
    "financial": {
      "revenue_latest_q": 68127000000.0,
      "revenue_yoy_pct": 19.5,
      "operating_income": 44299000000.0,
      "operating_margin_pct": 65.0,
      "diluted_eps": 1.76,
      "eps_consensus": "Data unavailable for eps_consensus",
      "eps_surprise_pct": "Data unavailable for eps_surprise_pct",
      "eps_consecutive_beats": 0,
      "eps_avg_surprise_8q": "Data unavailable for eps_avg_surprise_8q",
      "free_cash_flow": 34904000000.0,
      "price_to_fcf": "Data unavailable for price_to_fcf",
      "total_debt": 11040000000.0,
      "cash_and_equivalents": 10605000000.0,
      "debt_to_equity": 0.0702,
      "roic": "Data unavailable for roic",
      "sources": [
        {
          "type": "api",
          "tool": "yfinance",
          "title": "NVDA Financial Statements"
        },
        {
          "type": "api",
          "tool": "Financial Modeling Prep (FMP)",
          "title": "NVDA Key Metrics"
        }
      ]
    },
    "valuation": {
      "pe_trailing": 34.11813,
      "pe_forward": 25.0,
      "pb": 25.883808,
      "ps": 18.85529,
      "ev_ebitda": 30.17,
      "peg": 0.6891,
      "price_to_fcf": "Data unavailable for price_to_fcf",
      "market_cap": 4071573684224,
      "analyst_target_low": 140.0,
      "analyst_target_mean": 268.22195,
      "analyst_target_high": 380.0,
      "buy_count": 56,
      "hold_count": "Data unavailable for hold_count",
      "sell_count": "Data unavailable for sell_count",
      "forward_estimates": [],
      "sources": [
        {
          "type": "api",
          "tool": "yfinance",
          "title": "NVDA Valuation Multiples"
        },
        {
          "type": "api",
          "tool": "Financial Modeling Prep (FMP)",
          "title": "NVDA Analyst Estimates"
        }
      ]
    },
    "events": {
      "next_earnings_date": "Data unavailable for next_earnings_date",
      "last_eps_surprise_pct": "Data unavailable for last_eps_surprise_pct",
      "dividend_yield": "Data unavailable for dividend_yield",
      "buyback_amount_last_year": "Data unavailable for buyback_amount_last_year",
      "insider_buy_count": 0,
      "insider_sell_count": 10,
      "insider_dominant_activity": "sell",
      "sources": [
        {
          "type": "api",
          "tool": "yfinance",
          "title": "NVDA Earnings Calendar"
        },
        {
          "type": "sec",
          "tool": "yfinance/edgar",
          "title": "NVDA Insider Transactions (Form 4)"
        },
        {
          "type": "api",
          "tool": "yfinance",
          "title": "NVDA Dividends & Buybacks"
        }
      ]
    },
    "news": {
      "articles_analyzed": 10,
      "positive_pct": 10.0,
      "negative_pct": 10.0,
      "neutral_pct": 80.0,
      "top_headlines": [
        {
          "title": "NVIDIA Corporation (NVDA) Latest Stock News & Headlines",
          "url": "https://finance.yahoo.com/quote/NVDA/news/",
          "published_date": "Data unavailable for published_date",
          "source_name": "Data unavailable for source_name",
          "snippet": "-108.31-1.67%\n\nDow 30\n\n45,166.64\n\n-793.47-1.73%\n\nNasdaq\n\n20,948.36\n\n-459.72-2.15%\n\nRussell 2000\n\n2,449.70\n\n-43.63-1.75%\n\nVIX\n\n31.05\n\n+3.61+13.16%\n\nGold\n\n4,524.30\n\n+115.30+2.62%\n\nBitcoin USD\n\n66,565.44\n\n+259.34+0.39%\n\nCBOE Interest Rate 10 Year T No\n\n4.4400\n\n+0.0240+0.54%\n\nNVDA\n\nNVIDIA Corporation\n\n166.59-0.56%\n\n   Summary\n   News\n   Research\n   Chart\n   Community\n   Statistics\n   Historical Data\n "
        },
        {
          "title": "NVIDIA Corporation (NVDA) Stock Price, News, Quote & History",
          "url": "https://finance.yahoo.com/quote/NVDA/",
          "published_date": "Data unavailable for published_date",
          "source_name": "Data unavailable for source_name",
          "snippet": "NVDA\n\nDate\nClose\nOpen\nHigh\nLow\nVolume\n\n## News headlines Nvidia is experiencing a significant valuation shift, now trading at 19.7 times forward earnings, closely aligning with the S&P 500. Despite strong fundamentals, investors are cautious about competition and sustainability in the AI sector.\n\nNvidia is experiencing a significant valuation shift, now trading at 19.7 times forward earnings, clos"
        }
      ],
      "analyst_upgrades_30d": 0,
      "analyst_downgrades_30d": 0,
      "net_rating_change": 0,
      "rating_changes": [
        {
          "date": "2026-03-23",
          "analyst_firm": "Rosenblatt",
          "from_rating": "Buy",
          "to_rating": "Buy",
          "new_price_target": "Data unavailable for new_price_target",
          "action": "main"
        },
        {
          "date": "2026-03-23",
          "analyst_firm": "Cantor Fitzgerald",
          "from_rating": "Overweight",
          "to_rating": "Overweight",
          "new_price_target": "Data unavailable for new_price_target",
          "action": "reit"
        }
      ],
      "sources": [
        {
          "type": "news",
          "tool": "tavily",
          "title": "NVIDIA Corporation (NVDA) Latest Stock News & Headlines"
        },
        {
          "type": "news",
          "tool": "tavily",
          "title": "NVIDIA Corporation (NVDA) Stock Price, News, Quote & History"
        }
      ]
    },
    "sec": {
      "form_10k_filed_date": "2026-02-25",
      "form_10k_accession": "000104581026000021",
      "form_10q_filed_date": "Data unavailable for form_10q_filed_date",
      "form_10q_accession": "Data unavailable for form_10q_accession",
      "top_risk_factors": [
        "We discuss many of these risks, uncertainties, and other factors in this Annual Report on Form 10-K in greater detail under the heading Risk Factors."
      ],
      "guidance_summary": [
        "You should read this Annual Report on Form 10-K completely and understand that our actual future results may be materially different from what we expect.",
        "Researchers and developers use our computing solutions to accelerate a wide range of important applications, from simulating molecular dynamics to climate forecasting.",
        "With the advent of generative and agentic AI, we expect a broader set of PC users to choose NVIDIA GPUs for running these applications locally on their PC, which is critical for privacy, latency, and cost-sensitive AI applications."
      ],
      "liquidity_commentary": "Data unavailable for liquidity_commentary",
      "sources": [
        {
          "type": "sec",
          "tool": "edgar",
          "id": "000104581026000021",
          "title": "NVDA 10-K filed 2026-02-25 (SEC EDGAR)"
        }
      ]
    },
    "competitors": {
      "peers": [
        {
          "ticker": "AMD",
          "company_name": "Advanced Micro Devices, Inc.",
          "pe": 77.39081,
          "pb": 5.226132,
          "operating_margin": 0.17059,
          "revenue_growth": 0.341,
          "ev_ebitda": 47.855
        },
        {
          "ticker": "INTC",
          "company_name": "Intel Corporation",
          "pe": "Data unavailable for pe",
          "pb": 1.884723,
          "operating_margin": 0.051409997,
          "revenue_growth": -0.041,
          "ev_ebitda": 18.777
        },
        {
          "ticker": "QCOM",
          "company_name": "QUALCOMM Incorporated",
          "pe": 25.627016,
          "pb": 5.9167714,
          "operating_margin": 0.27473,
          "revenue_growth": 0.05,
          "ev_ebitda": 10.071
        }
      ],
      "sector_avg_pe": 51.51,
      "sector_avg_operating_margin": "Data unavailable for sector_avg_operating_margin",
      "sources": [
        {
          "type": "api",
          "tool": "yfinance",
          "title": "Competitor Comparison"
        }
      ]
    }
  },
  "data_gaps": []
}